qronos/__init__.py
qronos_client-1.8.2.dist-info/LICENSE
qronos_client-1.8.2.dist-info/METADATA
qronos_client-1.8.2.dist-info/WHEEL
qronos_client-1.8.2.dist-info/top_level.txt
qronos_client-1.8.2.dist-info/RECORD
