Metadata-Version: 2.1
Name: qronos-client
Version: 1.8.2
Summary: Python Client for QRonos
Home-page: https://github.com/QuickRelease/qronos-client.git
Author: Nick Solly
Author-email: nick.solly@quickrelease.co.uk
License: All Rights Reserved
Classifier: Environment :: Web Environment
Classifier: Intended Audience :: Developers
Classifier: Operating System :: OS Independent
Classifier: Programming Language :: Python
Classifier: Programming Language :: Python :: 3
Classifier: Programming Language :: Python :: 3 :: Only
Classifier: Programming Language :: Python :: 3.6
Classifier: Programming Language :: Python :: 3.7
Classifier: Programming Language :: Python :: 3.8
Classifier: Topic :: Internet :: WWW/HTTP
Classifier: Topic :: Internet :: WWW/HTTP :: Dynamic Content
License-File: LICENSE
Requires-Dist: requests >=2.24.0
Requires-Dist: python-dateutil >=2.8.0
